mtgscan/box_text.py
mtgscan/deck.py
mtgscan/ocr/azure.py
mtgscan/ocr/ocr.py
mtgscan/text.py
mtgscan-1.0.7.dist-info/LICENSE
mtgscan-1.0.7.dist-info/WHEEL
mtgscan-1.0.7.dist-info/METADATA
mtgscan-1.0.7.dist-info/RECORD
