Metadata-Version: 2.1
Name: mtgscan
Version: 1.0.7
Summary: Convert an image containing Magic cards to decklist
Home-page: https://github.com/fortierq/MTGScan
License: MIT
Keywords: mtg,scan,OCR,magic,cards,computer vision
Author: qfortier
Author-email: qpfortier@gmail.com
Requires-Python: >=3.8,<4.0
Classifier: License :: OSI Approved :: MIT License
Classifier: Programming Language :: Python :: 3
Classifier: Programming Language :: Python :: 3.8
Classifier: Programming Language :: Python :: 3.9
Requires-Dist: matplotlib (>=3.3.3,<4.0.0)
Requires-Dist: numpy (==1.19.3)
Requires-Dist: psutil (>=5.8.0,<6.0.0)
Requires-Dist: requests (>=2.25.0,<3.0.0)
Requires-Dist: symspellpy (>=6.7.0,<7.0.0)
Project-URL: Repository, https://github.com/fortierq/MTGScan
